logfmt/__init__.py
logfmt/logger.py
pylogfmt_rj-1.0.0.dist-info/METADATA
pylogfmt_rj-1.0.0.dist-info/WHEEL
pylogfmt_rj-1.0.0.dist-info/RECORD
