Metadata-Version: 2.4
Name: pylogfmt-rj
Version: 1.0.0
Summary: Beautiful, structured console logging
Project-URL: Homepage, https://github.com/RedJohnx/pypi_warehouse
Project-URL: Repository, https://github.com/RedJohnx/pypi_warehouse/tree/main/packages/logfmt
Author-email: RedJohnx <redjohnx@example.com>
License-Expression: MIT
Keywords: colored,console,logger,logging,structured
Classifier: Development Status :: 5 - Production/Stable
Classifier: Intended Audience :: Developers
Classifier: License :: OSI Approved :: MIT License
Classifier: Programming Language :: Python :: 3
Classifier: Programming Language :: Python :: 3.8
Classifier: Programming Language :: Python :: 3.9
Classifier: Programming Language :: Python :: 3.10
Classifier: Programming Language :: Python :: 3.11
Classifier: Programming Language :: Python :: 3.12
Requires-Python: >=3.8
